<?xml version="1.0" encoding="UTF-8"?>
<!--
  Copyright (C) 2008-2019  GMVIS Skysoft S.A.

  The license and distribution terms for this file may be
  found in the file LICENSE in this distribution or at
  air/LICENSE
-->
<IOPartition xmlns:xsi="http://www.w3.org/2001/XMLSchema-instance" xsi:schemaLocation="iop.xsd" version="1.0" date="2013-06-05" name="iop_example" request_number="64" time_to_live="5">
	
	<RemotePorts>
		<Port Name="dsampling" LogicalDeviceId="1"/>
		<Port Name="squeuing" />
	</RemotePorts>	
	
	<LogicalDevices>
		<Device Id="1" Name="PARSERVER" />
	</LogicalDevices>	
	
	<PhysicalDevices>
        <!-- Ip and port of board, beware it cannot be 46 that is EDCL -->        
		<Device Id="0" Device="ETH0" Ip="192.168.0.17" MAC="00:50:C2:75:a3:30" TXD="32" RXD="32">
			<PhysicalRoute Id="2" PortId="squeuing">
<!-- IP and port for destination PC, sets ONLY port number to used by sender.py -->
				<EthHeader Ip="192.168.0.3" MAC="00:60:67:90:3a:f6" Port="14000" />
			</PhysicalRoute>
			<LogicalRoute Id="1" LogicalDeviceId="1">
<!-- IP and port for destination PC, used by receiver.py -->
				<EthHeader Ip="192.168.0.3" MAC="00:60:67:90:3a:f6" Port="13000"/>
			</LogicalRoute>
	    </Device>		
	</PhysicalDevices>
	
	<ModuleSchedules>
		<Schedule ScheduleIdentifier="1">
		    <DevicesConfiguration>
			    <Device DeviceId="0" Device="ETH0" Reads="5"/>
			</DevicesConfiguration>
			<RoutesConfiguration>
				<Route RouteId="1" Active="true"/>
				<Route RouteId="2" Active="true"/>
			</RoutesConfiguration>
		</Schedule>
	</ModuleSchedules>
</IOPartition>
